{
  "title": "IMG_20241116_130354.jpg",
  "description": "",
  "imageViews": "15",
  "creationTime": {
    "timestamp": "1731810626",
    "formatted": "Nov 17, 2024, 2:30:26 AM UTC"
  },
  "photoTakenTime": {
    "timestamp": "1731791038",
    "formatted": "Nov 16, 2024, 9:03:58 PM UTC"
  },
  "geoData": {
    "latitude": 33.64895,
    "longitude": -117.842575,
    "altitude": -18.487,
    "latitudeSpan": 0.0,
    "longitudeSpan": 0.0
  },
  "geoDataExif": {
    "latitude": 33.64895,
    "longitude": -117.842575,
    "altitude": -18.487,
    "latitudeSpan": 0.0,
    "longitudeSpan": 0.0
  },
  "url": "https://photos.google.com/photo/AF1QipPrpKrLYK3EjLIAESrWNPkJXS3cKKLuSeD_-mk",
  "googlePhotosOrigin": {
    "mobileUpload": {
      "deviceFolder": {
        "localFolderName": ""
      },
      "deviceType": "ANDROID_PHONE"
    }
  }
}